dnf_humbug/__init__.py
dnf_humbug/__main__.py
dnf_humbug/app.py
dnf_humbug-0.0.14.dist-info/COPYING
dnf_humbug-0.0.14.dist-info/METADATA
dnf_humbug-0.0.14.dist-info/WHEEL
dnf_humbug-0.0.14.dist-info/entry_points.txt
dnf_humbug-0.0.14.dist-info/top_level.txt
dnf_humbug-0.0.14.dist-info/RECORD
