Metadata-Version: 2.1
Name: dnf-humbug
Version: 0.0.14
Summary: List and sort user-installed files according to dnf
License: GPL-2.0-or-later
License-File: COPYING
Requires-Dist: textual (==0.27.0)
